{
    "nodes_number": 116,
    "number_leaves": 59,
    "leaf_ordering_kolo": [
        "21",
        "59",
        "8",
        "30",
        "31",
        "32",
        "29",
        "28",
        "33",
        "17",
        "18",
        "20",
        "19",
        "26",
        "24",
        "23",
        "22",
        "25",
        "27",
        "7",
        "16",
        "13",
        "15",
        "9",
        "11",
        "12",
        "10",
        "14",
        "54",
        "55",
        "58",
        "56",
        "57",
        "34",
        "35",
        "36",
        "37",
        "52",
        "51",
        "47",
        "50",
        "46",
        "48",
        "49",
        "39",
        "38",
        "40",
        "45",
        "44",
        "53",
        "42",
        "41",
        "43",
        "4",
        "1",
        "2",
        "3",
        "5",
        "6"
    ],
    "execution_time_kolo": 0.11300492286682129,
    "optimal_leaf_ordering": [
        "21",
        "59",
        "8",
        "30",
        "31",
        "32",
        "29",
        "28",
        "33",
        "17",
        "18",
        "20",
        "19",
        "26",
        "24",
        "23",
        "22",
        "25",
        "27",
        "7",
        "16",
        "13",
        "15",
        "9",
        "11",
        "12",
        "10",
        "14",
        "54",
        "55",
        "58",
        "56",
        "57",
        "34",
        "35",
        "36",
        "37",
        "52",
        "51",
        "47",
        "50",
        "46",
        "48",
        "49",
        "39",
        "38",
        "40",
        "45",
        "44",
        "53",
        "42",
        "41",
        "43",
        "4",
        "1",
        "2",
        "3",
        "5",
        "6"
    ],
    "radial_points_unordered": {
        "1000": [
            0,
            0
        ],
        "1001": [
            -0.02197961924090259,
            0.023284317625772176
        ],
        "1002": [
            -0.007531135491322494,
            0.0407591101062287
        ],
        "1003": [
            0.008578221076833016,
            0.05253057321019861
        ],
        "1004": [
            0.10765495249362159,
            0.1186702535993352
        ],
        "1005": [
            0.17508676589657857,
            0.15665138870350093
        ],
        "1006": [
            0.2760385709714892,
            0.1953090730655117
        ],
        "1007": [
            0.3281892289931485,
            0.2117914972884087
        ],
        "1008": [
            0.40599543518800085,
            0.22392750617206658
        ],
        "1009": [
            0.52089391151666,
            0.2311718883064831
        ],
        "0": [
            0.7331426935284574,
            0.24288164508922588
        ],
        "1": [
            0.5509709523536542,
            0.23474001522298754
        ],
        "2": [
            0.6405946122781171,
            0.2685223437729054
        ],
        "1010": [
            0.42540258720855273,
            0.2543808514672771
        ],
        "3": [
            0.5890997265798326,
            0.3150123227735277
        ],
        "4": [
            0.6267044880299292,
            0.3536586155754857
        ],
        "5": [
            0.41464299023037293,
            0.3023586834140785
        ],
        "1011": [
            0.2870923122105141,
            0.2739752789003267
        ],
        "6": [
            0.44508283747191935,
            0.4332951190117945
        ],
        "7": [
            0.33452113730311717,
            0.32982557790040157
        ],
        "1012": [
            0.13101685269966898,
            0.16124437141221631
        ],
        "1013": [
            0.15766842498543043,
            0.20626305215821034
        ],
        "8": [
            0.15789647508709342,
            0.2066394226618786
        ],
        "9": [
            0.1777760253441399,
            0.2402367811584662
        ],
        "1014": [
            0.1459582875006643,
            0.1877702975917337
        ],
        "10": [
            0.1462657793911293,
            0.18830237667316638
        ],
        "1015": [
            0.14615950110965903,
            0.18812756175794032
        ],
        "11": [
            0.14636431982508857,
            0.18848219412351033
        ],
        "1016": [
            0.14631040300277473,
            0.1883955116955296
        ],
        "12": [
            0.14646390387721334,
            0.188661404083436
        ],
        "1017": [
            0.14646130493062653,
            0.18866346161355646
        ],
        "13": [
            0.1466147634719715,
            0.18892937843605606
        ],
        "1018": [
            0.16671045127915507,
            0.2237581657397672
        ],
        "14": [
            0.16671070116082218,
            0.22375859882076707
        ],
        "15": [
            0.16671070116070988,
            0.22375859882083185
        ],
        "16": [
            0.025173493791153082,
            0.0938382229630258
        ],
        "1019": [
            -0.003782030856610097,
            0.08900518168048621
        ],
        "1020": [
            0.01454439910303414,
            0.16011129225876458
        ],
        "1021": [
            0.028506450233990878,
            0.2055253227771952
        ],
        "17": [
            0.030191034618527915,
            0.21083438900938462
        ],
        "18": [
            0.038644838945222776,
            0.23867256121996094
        ],
        "19": [
            0.04722667103580659,
            0.28593472530265635
        ],
        "1022": [
            -0.0012775563664620682,
            0.13665856439620427
        ],
        "20": [
            0.0075330889701812065,
            0.18419822787166742
        ],
        "1023": [
            0.016902739183876282,
            0.33471260814704706
        ],
        "21": [
            0.021537360069582415,
            0.362836063784187
        ],
        "1024": [
            0.018074718992094,
            0.34805400056320923
        ],
        "22": [
            0.032284531967958906,
            0.45951268050102223
        ],
        "1025": [
            0.03281288139015832,
            0.49846667715926074
        ],
        "23": [
            0.03281293014913525,
            0.49846717477614366
        ],
        "24": [
            0.032812930149006235,
            0.4984671747761563
        ],
        "1026": [
            -0.1873936052310145,
            0.02048386919754666
        ],
        "1027": [
            -0.35803260833088035,
            0.32546763803874923
        ],
        "1028": [
            -0.36829956044889456,
            0.3444637567354937
        ],
        "1029": [
            -0.4005777062243038,
            0.44563855799738417
        ],
        "25": [
            -0.4690793899081427,
            0.7046966580137497
        ],
        "26": [
            -0.47225530239631003,
            0.6259848271968098
        ],
        "1030": [
            -0.38366154165250577,
            0.3678857267725229
        ],
        "27": [
            -0.4576596920008858,
            0.5132349584303303
        ],
        "28": [
            -0.6302145289791574,
            0.711216090164799
        ],
        "29": [
            -0.38322179592687333,
            0.349400002590886
        ],
        "1031": [
            -0.21234586741498565,
            0.014358260436944659
        ],
        "1032": [
            -0.30209688538109625,
            0.05185694384757908
        ],
        "1033": [
            -0.4200607434376028,
            0.11886965484507542
        ],
        "1034": [
            -0.5551004637882686,
            0.21758504290135613
        ],
        "30": [
            -0.7943448878664003,
            0.40365897386121585
        ],
        "31": [
            -0.6529061700035979,
            0.27790798663390875
        ],
        "32": [
            -0.6673164474541778,
            0.23879932109610746
        ],
        "33": [
            -0.6254340554776413,
            0.12007890336823468
        ],
        "1035": [
            -0.22748226499366395,
            0.004978943053457618
        ],
        "1036": [
            -0.30916965983479106,
            -0.004053671686621832
        ],
        "1037": [
            -0.3186391746191562,
            -0.00481537356970307
        ],
        "1038": [
            -0.350287213231554,
            -0.006112512976350821
        ],
        "1039": [
            -0.3887316750750346,
            -0.005841086114076272
        ],
        "1040": [
            -0.49536962660952744,
            -0.0016013614334920798
        ],
        "34": [
            -0.4976987473533439,
            -0.0014817505776974465
        ],
        "35": [
            -0.5399688661940845,
            0.00014481058191369496
        ],
        "36": [
            -0.40803798390260915,
            -0.005405589451957784
        ],
        "37": [
            -0.4966437451240731,
            -0.017234936835228414
        ],
        "38": [
            -0.4369187982978872,
            -0.024502021690972313
        ],
        "1041": [
            -0.36234442692296265,
            -0.016263126787469082
        ],
        "39": [
            -0.40728654421242977,
            -0.02652065798193208
        ],
        "40": [
            -0.3672285438263754,
            -0.01744619280566004
        ],
        "1042": [
            -0.31733236624481675,
            -0.06560099505636006
        ],
        "1043": [
            -0.3903705919659441,
            -0.09275270122995538
        ],
        "1044": [
            -0.4187569753939527,
            -0.1022926953864619
        ],
        "41": [
            -0.5126558938281295,
            -0.13109591123373693
        ],
        "42": [
            -0.5150777932165902,
            -0.1374178744497533
        ],
        "43": [
            -0.47538700501491393,
            -0.12871691954582948
        ],
        "1045": [
            -0.3613705768639701,
            -0.10378246994053905
        ],
        "44": [
            -0.3971101150251707,
            -0.12104447298849635
        ],
        "1046": [
            -0.404231143574362,
            -0.14061666161012976
        ],
        "1047": [
            -0.47064304393486994,
            -0.17780285077697458
        ],
        "45": [
            -0.5651831995882737,
            -0.2279859136033176
        ],
        "46": [
            -0.5449732338598965,
            -0.22217568026260776
        ],
        "1048": [
            -0.4480226697160408,
            -0.1794305524280143
        ],
        "47": [
            -0.798320439225495,
            -0.4610665015120071
        ],
        "1049": [
            -0.4812538802050217,
            -0.21569354091587406
        ],
        "48": [
            -0.5448445407401801,
            -0.28354691452965364
        ],
        "49": [
            -0.5096123911319316,
            -0.24817800657674696
        ],
        "1050": [
            0.03823098551110612,
            -0.13801487574166232
        ],
        "50": [
            0.03506340406295796,
            -0.2375558292772044
        ],
        "1051": [
            0.05565176620327897,
            -0.19866817783269128
        ],
        "51": [
            0.10362937337368774,
            -0.6383586524125917
        ],
        "1052": [
            0.09830613183743356,
            -0.3108846880547413
        ],
        "52": [
            0.1079878243506617,
            -0.35146892433886645
        ],
        "1053": [
            0.13004479194943108,
            -0.3978156598886343
        ],
        "53": [
            0.13166013314437613,
            -0.4042297096368678
        ],
        "1054": [
            0.1778908961654641,
            -0.5465284428838342
        ],
        "54": [
            0.20166988017079135,
            -0.6319745668344663
        ],
        "55": [
            0.2283187596639492,
            -0.691726161523041
        ],
        "1055": [
            0.10984766959469425,
            -0.06971606366391454
        ],
        "56": [
            0.2316865518250541,
            -0.2298965717083673
        ],
        "1056": [
            0.21993946342808463,
            -0.1367229743599791
        ],
        "57": [
            0.3875562535816519,
            -0.31125414423409237
        ],
        "58": [
            1.103635640092766,
            -0.6013010082073134
        ]
    },
    "radial_points_ordered_no_correction": {
        "1000": [
            0,
            0
        ],
        "1055": [
            0.11946579292975427,
            0.051524405555437275
        ],
        "1056": [
            0.24173884185229197,
            0.09226051555223011
        ],
        "57": [
            0.48324727397171574,
            0.10743268791578059
        ],
        "58": [
            1.167281100683496,
            0.4665908633773338
        ],
        "56": [
            0.27399163313595454,
            0.18045955626729848
        ],
        "1001": [
            -0.0320197295996815,
            -5.0632183977176756e-06
        ],
        "1002": [
            -0.03481270690634881,
            0.022496632999028682
        ],
        "1003": [
            -0.03231778234571083,
            0.042291937090777956
        ],
        "1004": [
            -0.012422023307182797,
            0.15974326659577942
        ],
        "1005": [
            0.006234613640118753,
            0.23485349213417522
        ],
        "1006": [
            0.04740480358327005,
            0.33480697615629645
        ],
        "1007": [
            0.0712095107475222,
            0.38404819219712755
        ],
        "1008": [
            0.1157833853077397,
            0.4489655099232174
        ],
        "1009": [
            0.18937226357851644,
            0.537502609096421
        ],
        "0": [
            0.3265274327101272,
            0.6999068068558439
        ],
        "1": [
            0.20741980350647404,
            0.5618263879506878
        ],
        "2": [
            0.2443610281135153,
            0.6501948894941818
        ],
        "1010": [
            0.10695442741523802,
            0.4839811248935498
        ],
        "4": [
            0.19203256547740763,
            0.6916834121811452
        ],
        "3": [
            0.1560872694364415,
            0.6514890130242894
        ],
        "5": [
            0.06467580602800016,
            0.5090841019887663
        ],
        "1011": [
            -0.002222285410804759,
            0.39683688163582287
        ],
        "6": [
            -0.009661998569243855,
            0.6210877861906062
        ],
        "7": [
            -0.010290352287916776,
            0.4696630832732071
        ],
        "1012": [
            -0.027352117696446077,
            0.20595393820213123
        ],
        "1013": [
            -0.041802346977927465,
            0.25623493655265644
        ],
        "9": [
            -0.052702269263144294,
            0.2941785993772262
        ],
        "8": [
            -0.0419282211280267,
            0.2566566204428358
        ],
        "1014": [
            -0.03638961568088864,
            0.2350261734752367
        ],
        "1015": [
            -0.03651122947882392,
            0.23541775320537062
        ],
        "11": [
            -0.036628454647110856,
            0.23581014724306754
        ],
        "1016": [
            -0.03660244685319484,
            0.235711433203009
        ],
        "1017": [
            -0.03669361743328752,
            0.2360051277309212
        ],
        "13": [
            -0.036781554464140644,
            0.23629928476212178
        ],
        "1018": [
            -0.04830178206288135,
            0.27482415269913296
        ],
        "15": [
            -0.04830192531166678,
            0.27482463173961713
        ],
        "14": [
            -0.04830192531179098,
            0.27482463173958
        ],
        "12": [
            -0.03669659099210215,
            0.23600366284132346
        ],
        "10": [
            -0.03657838356194309,
            0.235611003449402
        ],
        "16": [
            -0.05097088545314758,
            0.08271206510923224
        ],
        "1019": [
            -0.06732873489907568,
            0.05833581730178036
        ],
        "1020": [
            -0.10646597646295264,
            0.12046643229476783
        ],
        "19": [
            -0.1732337133245978,
            0.23200896461321804
        ],
        "1021": [
            -0.13264313206731454,
            0.1601165213763503
        ],
        "17": [
            -0.13567004197501528,
            0.16479218445414612
        ],
        "18": [
            -0.151782867132164,
            0.18901629444966306
        ],
        "1022": [
            -0.10026792380892019,
            0.09286301108702848
        ],
        "1023": [
            -0.228053684420778,
            0.24526618289525354
        ],
        "21": [
            -0.2447530808284154,
            0.268364637981016
        ],
        "1024": [
            -0.23669874831908672,
            0.25549502244170547
        ],
        "1025": [
            -0.3261482634007886,
            0.3773144419252529
        ],
        "23": [
            -0.3261485593305107,
            0.3773148449458474
        ],
        "24": [
            -0.3261485593306152,
            0.37731484494577067
        ],
        "22": [
            -0.3058104345840446,
            0.34408695740140105
        ],
        "20": [
            -0.13459519303038484,
            0.1269112953669373
        ],
        "1026": [
            -0.14351070975895122,
            -0.12223186312603428
        ],
        "1027": [
            -0.48243770408606645,
            -0.037018829194084196
        ],
        "1028": [
            -0.5032999528382395,
            -0.031448424510683304
        ],
        "1029": [
            -0.5990371848983582,
            0.014514620455338675
        ],
        "25": [
            -0.8344632824695027,
            0.14249169822331997
        ],
        "26": [
            -0.7793962608480212,
            0.08615998548150501
        ],
        "1030": [
            -0.5308779467907142,
            -0.02654603769680731
        ],
        "28": [
            -0.9435409339445864,
            0.06496009881879239
        ],
        "27": [
            -0.6936208036378201,
            -0.015734564913748833
        ],
        "29": [
            -0.517131561631128,
            -0.03891342504689345
        ],
        "1031": [
            -0.15618094260966084,
            -0.14458367894252666
        ],
        "1032": [
            -0.24505190736940685,
            -0.1841228760279011
        ],
        "1033": [
            -0.3747514537917849,
            -0.22392492246572882
        ],
        "1034": [
            -0.5392277910775022,
            -0.25438782424088924
        ],
        "30": [
            -0.8387578489417495,
            -0.3006819563871157
        ],
        "31": [
            -0.650226861544738,
            -0.28412029915048304
        ],
        "32": [
            -0.6316734523028966,
            -0.32144207324892393
        ],
        "33": [
            -0.5165837462174334,
            -0.3724619899121111
        ],
        "1035": [
            -0.15974789709309212,
            -0.1620295656197102
        ],
        "1036": [
            -0.209242611323406,
            -0.22763971626907592
        ],
        "1037": [
            -0.2151877927842938,
            -0.23504962297612128
        ],
        "1038": [
            -0.23596522565987008,
            -0.25895734561448697
        ],
        "1039": [
            -0.26254802340385563,
            -0.28673152756605413
        ],
        "1040": [
            -0.3388198327460822,
            -0.36137895935377906
        ],
        "35": [
            -0.37073713720788576,
            -0.3925787504447565
        ],
        "34": [
            -0.3404676047246128,
            -0.36302940102280873
        ],
        "36": [
            -0.27611515791052615,
            -0.30047401930395634
        ],
        "37": [
            -0.32832406908971495,
            -0.3730353311349366
        ],
        "38": [
            -0.28204803741213236,
            -0.3345852506686138
        ],
        "1041": [
            -0.23685789954187064,
            -0.2746931168406821
        ],
        "39": [
            -0.26024254015396964,
            -0.3144192975796931
        ],
        "40": [
            -0.2393495523202548,
            -0.27905727879477715
        ],
        "1042": [
            -0.17008181266307965,
            -0.27581787146622705
        ],
        "1043": [
            -0.2004624604851549,
            -0.34757310683298365
        ],
        "1044": [
            -0.2130063503666821,
            -0.3747659198406189
        ],
        "42": [
            -0.2583083207390046,
            -0.46673988153976076
        ],
        "41": [
            -0.25176215311870365,
            -0.46501346761505596
        ],
        "43": [
            -0.23265473922574506,
            -0.43408826548320545
        ],
        "1045": [
            -0.17253713205600021,
            -0.3340515423581333
        ],
        "1046": [
            -0.1763252920986133,
            -0.39043802742485517
        ],
        "1048": [
            -0.1851962179374822,
            -0.44827851978964484
        ],
        "1049": [
            -0.19885878723171196,
            -0.49552946565228306
        ],
        "49": [
            -0.21183180050111125,
            -0.5366530182465823
        ],
        "48": [
            -0.22368935040318377,
            -0.5851469614366245
        ],
        "47": [
            -0.24330511593133533,
            -0.8939809890599868
        ],
        "1047": [
            -0.1715641956121446,
            -0.46640305315704944
        ],
        "46": [
            -0.16854861767583273,
            -0.552917973376406
        ],
        "45": [
            -0.162473286236211,
            -0.5730498355385215
        ],
        "44": [
            -0.16492867170523767,
            -0.3730053954190883
        ],
        "1050": [
            0.12661641990359138,
            -0.06691783312342327
        ],
        "1051": [
            0.18111603814117194,
            -0.09873132501646095
        ],
        "1052": [
            0.27490130197545976,
            -0.1736730647987787
        ],
        "52": [
            0.3038729666026821,
            -0.20369735585475793
        ],
        "1053": [
            0.34643082781785073,
            -0.23239157416722844
        ],
        "1054": [
            0.46288651967968764,
            -0.33652040469849775
        ],
        "54": [
            0.5265957796124182,
            -0.3982262421641393
        ],
        "55": [
            0.5797930200788041,
            -0.4363112714122581
        ],
        "53": [
            0.3516357095510516,
            -0.23647306500910123
        ],
        "51": [
            0.5850433253685898,
            -0.27893207656648944
        ],
        "50": [
            0.22387480172426388,
            -0.0883477693953743
        ]
    },
    "radial_points_ordered_pivot_based_angle_correction": {
        "1000": [
            0,
            0
        ],
        "1055": [
            0.12129079304629256,
            0.047067861332097186
        ],
        "1056": [
            0.24470236656059907,
            0.08421234508415679
        ],
        "57": [
            0.48629340657059905,
            0.09800679998089581
        ],
        "58": [
            1.1787962936290546,
            0.4366612315897911
        ],
        "56": [
            0.27642650597098345,
            0.17526855928601004
        ],
        "1001": [
            -0.03130676449422381,
            0.00671934566577043
        ],
        "1002": [
            -0.032292767628861796,
            0.029372267170851934
        ],
        "1003": [
            -0.02866695204431238,
            0.0489919555984223
        ],
        "1004": [
            -0.0025177328357368425,
            0.16521103477647064
        ],
        "1005": [
            0.01961995360334076,
            0.23936991099326063
        ],
        "1006": [
            0.06408983997059352,
            0.3378996664714878
        ],
        "1007": [
            0.0892554885878904,
            0.38645943963844503
        ],
        "1008": [
            0.13473807755848208,
            0.4507433609142377
        ],
        "1009": [
            0.20883255742332707,
            0.5388577694335882
        ],
        "0": [
            0.34679970697758744,
            0.7005727332225797
        ],
        "1": [
            0.2268974573885238,
            0.563168658032114
        ],
        "2": [
            0.2644463143766788,
            0.65124584651858
        ],
        "1010": [
            0.1259386731793833,
            0.48605177906832314
        ],
        "4": [
            0.21211444126274231,
            0.6933010654744951
        ],
        "3": [
            0.1757603162316451,
            0.6533560905330129
        ],
        "5": [
            0.08208008881566921,
            0.5121040150405308
        ],
        "1011": [
            0.012299664209696054,
            0.4014086439529863
        ],
        "6": [
            0.006046015116744706,
            0.6256957577124278
        ],
        "7": [
            0.004357382766340748,
            0.47424867081690936
        ],
        "1012": [
            -0.01726705830684133,
            0.21147972059020248
        ],
        "1013": [
            -0.03166997254205157,
            0.26177429269242913
        ],
        "9": [
            -0.04253458304869127,
            0.2997280816061518
        ],
        "8": [
            -0.031795842318196474,
            0.2621959778882248
        ],
        "1014": [
            -0.026274961779350597,
            0.24056113920456096
        ],
        "1015": [
            -0.026396186422332844,
            0.24095283958346533
        ],
        "11": [
            -0.026513407802937466,
            0.24134523475268782
        ],
        "1016": [
            -0.02648711690027812,
            0.24124660853788468
        ],
        "1017": [
            -0.02657800482518384,
            0.24154039066039443
        ],
        "13": [
            -0.02666593972735309,
            0.24183454832794787
        ],
        "1018": [
            -0.03818616853980226,
            0.2803594159022139
        ],
        "15": [
            -0.03818631178858204,
            0.28035989494269975
        ],
        "14": [
            -0.03818631178870624,
            0.2803598949426626
        ],
        "12": [
            -0.026581258924449066,
            0.2415388388574701
        ],
        "10": [
            -0.026463721189192203,
            0.24114597191294537
        ],
        "16": [
            -0.0472776333380347,
            0.08943163346989395
        ],
        "1019": [
            -0.06404857107072973,
            0.06588675957690694
        ],
        "1020": [
            -0.10286642713238038,
            0.12821741854513116
        ],
        "19": [
            -0.16929207288276124,
            0.23996401038704512
        ],
        "1021": [
            -0.12900597070310302,
            0.16789231365055887
        ],
        "17": [
            -0.13203226674220345,
            0.17256837407468995
        ],
        "18": [
            -0.14812208775735283,
            0.19680771457826207
        ],
        "1022": [
            -0.09653524241865338,
            0.10084006359032599
        ],
        "1023": [
            -0.22322068296845018,
            0.25415909875903
        ],
        "21": [
            -0.23990455763706897,
            0.2772687675963418
        ],
        "1024": [
            -0.2318020528246686,
            0.26444143213544247
        ],
        "1025": [
            -0.32125156503505226,
            0.3862608537273402
        ],
        "23": [
            -0.3212518609647696,
            0.3862612567479382
        ],
        "24": [
            -0.32125186096487407,
            0.3862612567478615
        ],
        "22": [
            -0.30067887218753414,
            0.3532160899649384
        ],
        "20": [
            -0.13082368776977507,
            0.13492744527345826
        ],
        "1026": [
            -0.15739740578953057,
            -0.10038237911153829
        ],
        "1027": [
            -0.4936931313759455,
            -0.005314226779609826
        ],
        "1028": [
            -0.5143921083483014,
            0.0008351783649779504
        ],
        "1029": [
            -0.6096231275183874,
            0.04783807288125539
        ],
        "25": [
            -0.844236239510052,
            0.17729952480110922
        ],
        "26": [
            -0.7896525945085103,
            0.1203076914976188
        ],
        "1030": [
            -0.5418997875537356,
            0.006117860604761539
        ],
        "28": [
            -0.9536306481959036,
            0.10173068600819797
        ],
        "27": [
            -0.7045998788239805,
            0.01755489252525463
        ],
        "29": [
            -0.5283885288891209,
            -0.00718040903363581
        ],
        "1031": [
            -0.1720067612797136,
            -0.12151778076249015
        ],
        "1032": [
            -0.26207006510186526,
            -0.15826009680439063
        ],
        "1033": [
            -0.39254978495652104,
            -0.19542483747966155
        ],
        "1034": [
            -0.5573182657678366,
            -0.22426580907597285
        ],
        "30": [
            -0.8571713952694171,
            -0.2684189852181255
        ],
        "31": [
            -0.6683974597873287,
            -0.253697532858654
        ],
        "32": [
            -0.6500980336844926,
            -0.2912758030093367
        ],
        "33": [
            -0.5350606148577371,
            -0.34447857352157063
        ],
        "1035": [
            -0.1765299602119745,
            -0.1387405214752569
        ],
        "1036": [
            -0.22698577898344935,
            -0.2036144681493493
        ],
        "1037": [
            -0.23301956826284514,
            -0.21095240293659348
        ],
        "1038": [
            -0.25399812099812363,
            -0.23468384292209032
        ],
        "1039": [
            -0.2806939504318857,
            -0.2623493993021793
        ],
        "1040": [
            -0.3570483471705993,
            -0.33691235304937955
        ],
        "35": [
            -0.38899845683417883,
            -0.36807854917135346
        ],
        "34": [
            -0.3586962098720437,
            -0.33856270413726613
        ],
        "36": [
            -0.29426733871556476,
            -0.2760857142515711
        ],
        "37": [
            -0.34675107648908315,
            -0.3484416206245164
        ],
        "38": [
            -0.3001608567152948,
            -0.3102986704899236
        ],
        "1041": [
            -0.2546577459366286,
            -0.25063455846915894
        ],
        "39": [
            -0.2780855367869354,
            -0.290335307436148
        ],
        "40": [
            -0.25714991562884126,
            -0.25499842525846594
        ],
        "1042": [
            -0.19092882168177322,
            -0.2520861925297866
        ],
        "1043": [
            -0.22185487049496894,
            -0.32360805680520544
        ],
        "1044": [
            -0.23452728401530962,
            -0.3507412134257976
        ],
        "42": [
            -0.28005138203833574,
            -0.44260543197382596
        ],
        "41": [
            -0.2734919066023006,
            -0.4408987994233511
        ],
        "43": [
            -0.25423531109633835,
            -0.41005296731615504
        ],
        "1045": [
            -0.1948370819172217,
            -0.3102404229932715
        ],
        "1046": [
            -0.19990403771719528,
            -0.3665264053832877
        ],
        "1048": [
            -0.20963933940961407,
            -0.42422770331667553
        ],
        "1049": [
            -0.2234534320120047,
            -0.4714345728401482
        ],
        "49": [
            -0.23646823577154036,
            -0.5125449186713971
        ],
        "48": [
            -0.24848036715209956,
            -0.5609974275041348
        ],
        "47": [
            -0.2724667676720747,
            -0.8692895522743969
        ],
        "1047": [
            -0.19548963552936632,
            -0.4425123661100594
        ],
        "46": [
            -0.19265059048183517,
            -0.5290332592750614
        ],
        "45": [
            -0.18666780448189854,
            -0.5491817437335013
        ],
        "44": [
            -0.18726506634167286,
            -0.3492013767460641
        ],
        "1050": [
            0.12456594300256899,
            -0.07066144651093433
        ],
        "1051": [
            0.17822105000498112,
            -0.10387945588883209
        ],
        "1052": [
            0.27104578557695047,
            -0.18000769335734026
        ],
        "52": [
            0.2999879095666482,
            -0.21006046134385628
        ],
        "1053": [
            0.34201120975249444,
            -0.23940672517836512
        ],
        "1054": [
            0.45787007416131276,
            -0.3441992108475578
        ],
        "54": [
            0.5214501974792256,
            -0.40603809907649824
        ],
        "55": [
            0.5744142778468936,
            -0.44441295991596635
        ],
        "53": [
            0.3472154551113664,
            -0.243489027420184
        ],
        "51": [
            0.5802478026208918,
            -0.2882813387620864
        ],
        "50": [
            0.22177375236125316,
            -0.09231962747521
        ]
    },
    "radial_points_ordered_adjacent_node_based_angle_correction": {
        "1000": [
            0,
            0
        ],
        "1055": [
            0.11946579292975427,
            0.051524405555437275
        ],
        "1056": [
            0.24173884185229197,
            0.09226051555223011
        ],
        "57": [
            0.48182082382747526,
            0.1225451573675025
        ],
        "58": [
            1.0406286653378052,
            0.6910315336522346
        ],
        "56": [
            0.2803857431785401,
            0.17238497808614636
        ],
        "1001": [
            -0.0320197295996815,
            -5.0632183977176756e-06
        ],
        "1002": [
            -0.03481270690634881,
            0.022496632999028682
        ],
        "1003": [
            -0.03231778234571083,
            0.042291937090777956
        ],
        "1004": [
            -0.012422023307182797,
            0.15974326659577942
        ],
        "1005": [
            0.006234613640118753,
            0.23485349213417522
        ],
        "1006": [
            0.04740480358327005,
            0.33480697615629645
        ],
        "1007": [
            0.0712095107475222,
            0.38404819219712755
        ],
        "1008": [
            0.1157833853077397,
            0.4489655099232174
        ],
        "1009": [
            0.18937226357851644,
            0.537502609096421
        ],
        "0": [
            0.3173729482352692,
            0.7072155685214603
        ],
        "1": [
            0.20760663198742207,
            0.5616866477155351
        ],
        "2": [
            0.25633769799276507,
            0.6420197992245562
        ],
        "1010": [
            0.10695442741523802,
            0.4839811248935498
        ],
        "4": [
            0.17980828250414982,
            0.6962800780688028
        ],
        "3": [
            0.1484581350218505,
            0.6535404685051766
        ],
        "5": [
            0.07241844455315588,
            0.5081422636176268
        ],
        "1011": [
            -0.002222285410804759,
            0.39683688163582287
        ],
        "6": [
            -0.0226876773172237,
            0.6202758783656576
        ],
        "7": [
            -0.008931924743176493,
            0.46980077742060117
        ],
        "1012": [
            -0.027352117696446077,
            0.20595393820213123
        ],
        "1013": [
            -0.041802346977927465,
            0.25623493655265644
        ],
        "9": [
            -0.0530900692159402,
            0.2940650460032762
        ],
        "8": [
            -0.04192817393201032,
            0.2566566345281392
        ],
        "1014": [
            -0.03638961568088864,
            0.2350261734752367
        ],
        "1015": [
            -0.03651122947882392,
            0.23541775320537062
        ],
        "11": [
            -0.03662841377715267,
            0.2358101594503836
        ],
        "1016": [
            -0.03660244685319484,
            0.235711433203009
        ],
        "1017": [
            -0.03669361743328752,
            0.2360051277309212
        ],
        "13": [
            -0.0367815778793593,
            0.2362992777612235
        ],
        "1018": [
            -0.04830178206288135,
            0.27482415269913296
        ],
        "15": [
            -0.04830192531164607,
            0.27482463173962335
        ],
        "14": [
            -0.048301925311817595,
            0.27482463173957206
        ],
        "12": [
            -0.03669656817367497,
            0.2360036701914808
        ],
        "10": [
            -0.03657847674267004,
            0.23561097336489364
        ],
        "16": [
            -0.05143615974362804,
            0.08249408442441808
        ],
        "1019": [
            -0.06732873489907568,
            0.05833581730178036
        ],
        "1020": [
            -0.10646597646295264,
            0.12046643229476783
        ],
        "19": [
            -0.1769546401038655,
            0.2296956202426632
        ],
        "1021": [
            -0.13264313206731454,
            0.1601165213763503
        ],
        "17": [
            -0.13566341553260894,
            0.16479646759352728
        ],
        "18": [
            -0.1515273554645786,
            0.18918389911710676
        ],
        "1022": [
            -0.10026792380892019,
            0.09286301108702848
        ],
        "1023": [
            -0.228053684420778,
            0.24526618289525354
        ],
        "21": [
            -0.24492332096963176,
            0.26824059976354375
        ],
        "1024": [
            -0.23669874831908672,
            0.25549502244170547
        ],
        "1025": [
            -0.3261482634007886,
            0.3773144419252529
        ],
        "23": [
            -0.3261485593305629,
            0.377314844945809
        ],
        "24": [
            -0.32614855933056397,
            0.3773148449458083
        ],
        "22": [
            -0.30836161756333647,
            0.34203628017447973
        ],
        "20": [
            -0.1341739363373361,
            0.12733081329476
        ],
        "1026": [
            -0.14351070975895122,
            -0.12223186312603428
        ],
        "1027": [
            -0.48243770408606645,
            -0.037018829194084196
        ],
        "1028": [
            -0.5032999528382395,
            -0.031448424510683304
        ],
        "1029": [
            -0.5990371848983582,
            0.014514620455338675
        ],
        "25": [
            -0.825201975464843,
            0.15822637140016593
        ],
        "26": [
            -0.7827714299428974,
            0.07699807270521142
        ],
        "1030": [
            -0.5308779467907142,
            -0.02654603769680731
        ],
        "28": [
            -0.9510735353544779,
            0.019277333396125692
        ],
        "27": [
            -0.6930324708672198,
            -0.008995091283055676
        ],
        "29": [
            -0.517146948771142,
            -0.038606776987324155
        ],
        "1031": [
            -0.15618094260966084,
            -0.14458367894252666
        ],
        "1032": [
            -0.24505190736940685,
            -0.1841228760279011
        ],
        "1033": [
            -0.3747514537917849,
            -0.22392492246572882
        ],
        "1034": [
            -0.5392277910775022,
            -0.25438782424088924
        ],
        "30": [
            -0.8341993516680652,
            -0.32405259782194257
        ],
        "31": [
            -0.6510482722903905,
            -0.2808641096706483
        ],
        "32": [
            -0.6240793810665858,
            -0.33948483202206114
        ],
        "33": [
            -0.49947087801237405,
            -0.39500708288999176
        ],
        "1035": [
            -0.15974789709309212,
            -0.1620295656197102
        ],
        "1036": [
            -0.209242611323406,
            -0.22763971626907592
        ],
        "1037": [
            -0.2151877927842938,
            -0.23504962297612128
        ],
        "1038": [
            -0.23596522565987008,
            -0.25895734561448697
        ],
        "1039": [
            -0.26254802340385563,
            -0.28673152756605413
        ],
        "1040": [
            -0.3388198327460822,
            -0.36137895935377906
        ],
        "35": [
            -0.3703739565874833,
            -0.3929460079460948
        ],
        "34": [
            -0.34046858336873365,
            -0.36302842338200353
        ],
        "36": [
            -0.2761824879103212,
            -0.30040722116858604
        ],
        "37": [
            -0.33251720862933587,
            -0.3695089504186077
        ],
        "38": [
            -0.2850518501764159,
            -0.33250036425879786
        ],
        "1041": [
            -0.23685789954187064,
            -0.2746931168406821
        ],
        "39": [
            -0.2597660766928963,
            -0.31469594514422616
        ],
        "40": [
            -0.23935512801199157,
            -0.2790540907110025
        ],
        "1042": [
            -0.17008181266307965,
            -0.27581787146622705
        ],
        "1043": [
            -0.2004624604851549,
            -0.34757310683298365
        ],
        "1044": [
            -0.2130063503666821,
            -0.3747659198406189
        ],
        "42": [
            -0.26069085346101334,
            -0.4655275103671005
        ],
        "41": [
            -0.24945167355946152,
            -0.46597102136255547
        ],
        "43": [
            -0.23467678610435805,
            -0.43330872025709133
        ],
        "1045": [
            -0.17253713205600021,
            -0.3340515423581333
        ],
        "1046": [
            -0.1763252920986133,
            -0.39043802742485517
        ],
        "1048": [
            -0.1851962179374822,
            -0.44827851978964484
        ],
        "1049": [
            -0.19885878723171196,
            -0.49552946565228306
        ],
        "49": [
            -0.21137123011701542,
            -0.5367954858663299
        ],
        "48": [
            -0.22580172243226876,
            -0.5845346939304438
        ],
        "47": [
            -0.2937644143421282,
            -0.8844439492647262
        ],
        "1047": [
            -0.1715641956121446,
            -0.46640305315704944
        ],
        "46": [
            -0.17045393155808328,
            -0.5529633930627006
        ],
        "45": [
            -0.1595176198543674,
            -0.5727565243656312
        ],
        "44": [
            -0.16532225868487269,
            -0.3730802105322101
        ],
        "1050": [
            0.12661641990359138,
            -0.06691783312342327
        ],
        "1051": [
            0.18111603814117194,
            -0.09873132501646095
        ],
        "1052": [
            0.27490130197545976,
            -0.1736730647987787
        ],
        "52": [
            0.304196058082368,
            -0.2033821992412892
        ],
        "1053": [
            0.34643082781785073,
            -0.23239157416722844
        ],
        "1054": [
            0.46288651967968764,
            -0.33652040469849775
        ],
        "54": [
            0.5251877974321262,
            -0.39964750639757707
        ],
        "55": [
            0.583675980133229,
            -0.4315743533718406
        ],
        "53": [
            0.35162883634488706,
            -0.23648181483273426
        ],
        "51": [
            0.603009810510521,
            -0.23152894947584612
        ],
        "50": [
            0.2233008740787115,
            -0.09080404931298958
        ]
    },
    "unordered_tree_stress": 0.6035907032629868,
    "ordered_tree_stress": 0.6050301635549946,
    "ordered_tree_fixed_angle_correction_stress": 0.6041990738519626,
    "ordered_tree_adj_based_corrections_stress": 0.6044866541145704,
    "execution_time_radial_layout": 0.0017552375793457031,
    "execution_time_corrections_adj_based": 0.12293338775634766,
    "execution_time_corrections_fixed_based": 3.5064139366149902
}